devcore/__about__.py
devcore/__init__.py
devcore/__main__.py
devcore-0.1.3.dist-info/DESCRIPTION.rst
devcore-0.1.3.dist-info/METADATA
devcore-0.1.3.dist-info/RECORD
devcore-0.1.3.dist-info/WHEEL
devcore-0.1.3.dist-info/entry_points.txt
devcore-0.1.3.dist-info/metadata.json
devcore-0.1.3.dist-info/top_level.txt
