Metadata-Version: 2.0
Name: devcore
Version: 0.1.3
Summary: Meta package for python development environment
Home-page: https://github.com/paradoxxxzero/devcore
Author: Florian Mounier
Author-email: paradoxxx.zero@gmail.com
License: MIT
Platform: Any
Provides: devcore
Requires-Dist: better-exceptions
Requires-Dist: cutter
Requires-Dist: flask-wdb-hook
Requires-Dist: importmagic3
Requires-Dist: isort
Requires-Dist: log-colorizer-hook
Requires-Dist: pyls-isort
Requires-Dist: python-language-server
Requires-Dist: python-language-server
Requires-Dist: semver
Requires-Dist: wdb
